{"jei":{"curseForgeID":238222,"lastUpdated":"2022-06-27T10:28:19.906880","modID":"jei"},"mousetweaks":{"curseForgeID":60089,"lastUpdated":"2022-06-27T10:28:22.432173","modID":"mousetweaks"},"controlling":{"curseForgeID":250398,"lastUpdated":"2022-06-27T10:28:24.104339","modID":"controlling"},"journeymap":{"curseForgeID":32274,"lastUpdated":"2022-06-27T10:28:25.682","modID":"journeymap"},"appleskin":{"curseForgeID":248787,"lastUpdated":"2022-06-27T10:28:26.991639","modID":"appleskin"},"clumps":{"curseForgeID":256717,"lastUpdated":"2022-06-27T10:28:28.292653","modID":"clumps"},"bookshelf":{"curseForgeID":228525,"lastUpdated":"2022-06-27T10:28:29.598770","modID":"bookshelf"},"naturescompass":{"curseForgeID":252848,"lastUpdated":"2022-06-27T10:28:32.474784","modID":"naturescompass"},"waystones":{"curseForgeID":245755,"lastUpdated":"2022-06-27T10:28:33.609483","modID":"waystones"},"patchouli":{"curseForgeID":306770,"lastUpdated":"2022-06-27T10:28:35.296271","modID":"patchouli"}}